wbgLatLonChangePkg.py
wbgLatLonChangePkg-1.0.0.dist-info/LICENSE
wbgLatLonChangePkg-1.0.0.dist-info/WHEEL
wbgLatLonChangePkg-1.0.0.dist-info/METADATA
wbgLatLonChangePkg-1.0.0.dist-info/RECORD
