Metadata-Version: 2.1
Name: wbgLatLonChangePkg
Version: 1.0.0
Summary: this module is used to change each other latlon between wgs84,baidu09,gcj
Home-page: https://github.com/longsjj/wbgLatlonChangePkg
License: UNKNOWN
Author: longsjj
Author-email: rongjunzeng@gmail.com
Classifier: License :: OSI Approved :: MIT License
